{"skeleton": {"hash": "GwidT1w06KB+r92if2YdUSMGz2k", "spine": "2.1.27", "width": 394.02685546875, "height": 388.40570068359375}, "bones": [{"name": "root"}, {"name": "fxskill", "parent": "root"}, {"name": "polearm_trail", "parent": "fxskill", "x": -37.52683639526367, "y": 316.4039001464844}], "slots": [{"name": "attack_high", "bone": "root"}, {"name": "polearm_trail", "bone": "polearm_trail", "attachment": "polearm_trail"}], "skins": {"default": {"polearm_trail": {"polearm_trail": {"type": "mesh", "uvs": [0, 0, 0.5, 0, 1, 0, 1, 0.5, 1, 1, 0.5, 1, 0, 1, 0, 0.5, 0.5, 0.5], "triangles": [7, 0, 1, 8, 1, 2, 7, 1, 8, 8, 2, 3, 6, 7, 8, 5, 8, 3, 6, 8, 5, 5, 3, 4], "vertices": [-178.25, 72.5, 0, 72.5, 178.24000549316406, 72.5, 178.24000549316406, 0, 178.24000549316406, -72.48999786376953, 0, -72.48999786376953, -178.25, -72.48999786376953, -178.25, 0, 0, 0], "hull": 8}}}}, "animations": {"if_it_bleeds": {"slots": {"polearm_trail": {"color": [{"time": 0, "color": "ffffff00", "curve": [0.27000001072883606, -0.78700852394104, 0.75, 1]}, {"time": 0.10000000149011612, "color": "ffffffff", "curve": "stepped"}, {"time": 0.4333333373069763, "color": "ffffffff", "curve": [0.3699992895126343, -3.923635700109488e-44, 0.8357142806053162, 0.6437501907348633]}, {"time": 0.8333333134651184, "color": "ffffff00", "curve": "stepped"}, {"time": 1.8666666746139526, "color": "ffffff00"}]}}}}}